wurtzisms/__init__.py
wurtzisms/__main__.py
wurtzisms-1.0.0.dist-info/METADATA
wurtzisms-1.0.0.dist-info/RECORD
wurtzisms-1.0.0.dist-info/WHEEL
wurtzisms-1.0.0.dist-info/entry_points.txt
wurtzisms-1.0.0.dist-info/top_level.txt
