Metadata-Version: 2.1
Name: wurtzisms
Version: 1.0.0
Summary: Your daily wurtzisms delivered straight to your shell
Home-page: https://github.com/splump/wurtzisms
Author: Daniel Andersson
Author-email: wurtz@muthur6000.se
License: UNKNOWN
Platform: UNKNOWN
Classifier: Programming Language :: Python :: 3
Classifier: License :: OSI Approved :: GNU Lesser General Public License v3 (LGPLv3)
Classifier: Operating System :: OS Independent
Requires-Dist: beautifulsoup4 (==4.6.3)
Requires-Dist: requests (==2.19.1)
